<annotation>
	<folder>250</folder>
	<filename>austin20_3750.tif</filename>
	<path>E:\MUVA\2-trimestre\aplicaciones_industriales_y_comerciales\AIVA_2021-imagenes_aereas\images\250\austin20_3750.tif</path>
	<source>
		<database>Unknown</database>
	</source>
	<size>
		<width>250</width>
		<height>250</height>
		<depth>3</depth>
	</size>
	<segmented>0</segmented>
	<object>
		<name>tree</name>
		<pose>Unspecified</pose>
		<truncated>0</truncated>
		<difficult>0</difficult>
		<bndbox>
			<xmin>162</xmin>
			<ymin>84</ymin>
			<xmax>198</xmax>
			<ymax>126</ymax>
		</bndbox>
	</object>
	<object>
		<name>tree</name>
		<pose>Unspecified</pose>
		<truncated>0</truncated>
		<difficult>0</difficult>
		<bndbox>
			<xmin>61</xmin>
			<ymin>48</ymin>
			<xmax>106</xmax>
			<ymax>99</ymax>
		</bndbox>
	</object>
</annotation>
